rtl/fifo/sync_fifo.sv
// rtl/fifo/fifo.sv
module sync_fifo #(
    parameter DATA_WIDTH = 32,
    parameter ADDR_WIDTH = 4,   // Depth = 2^ADDR_WIDTH
    parameter FIFO_DEPTH = 16
) (
    input wire clk,
    input wire rst_n,

    // Write interface
    input wire wr_en,
    input wire [DATA_WIDTH-1:0] data_in,
    output wire full,

    // Read interface
    input wire rd_en,
    output wire [DATA_WIDTH-1:0] data_out,
    output wire empty
);

  // Internal memory
  reg [DATA_WIDTH-1:0] mem[0:FIFO_DEPTH-1];

  // Pointers
  reg [ADDR_WIDTH:0] wr_ptr = 0;  // MSB for full/empty detection
  reg [ADDR_WIDTH:0] rd_ptr = 0;

  // Status flags
  wire [ADDR_WIDTH:0] wr_ptr_gray;
  wire [ADDR_WIDTH:0] rd_ptr_gray;

  // Empty when pointers are equal
  assign empty = (wr_ptr == rd_ptr);

  // Full when pointers differ by FIFO_DEPTH
  assign full = ((wr_ptr[ADDR_WIDTH-1:0] == rd_ptr[ADDR_WIDTH-1:0]) &&
                   (wr_ptr[ADDR_WIDTH] != rd_ptr[ADDR_WIDTH]));

  // Data output
  assign data_out = mem[rd_ptr[ADDR_WIDTH-1:0]];

  // Write operation
  always_ff @(posedge clk or negedge rst_n) begin
    if (!rst_n) begin
      wr_ptr <= 0;
    end else if (wr_en && !full) begin
      mem[wr_ptr[ADDR_WIDTH-1:0]] <= data_in;
      wr_ptr <= wr_ptr + 1;
    end
  end

  // Read operation
  always_ff @(posedge clk or negedge rst_n) begin
    if (!rst_n) begin
      rd_ptr <= 0;
    end else if (rd_en && !empty) begin
      rd_ptr <= rd_ptr + 1;
    end
  end

  // Gray code conversion (for clock domain crossing if async)
  function [ADDR_WIDTH:0] binary_to_gray(input [ADDR_WIDTH:0] bin);
    binary_to_gray = bin ^ (bin >> 1);
  endfunction

  assign wr_ptr_gray = binary_to_gray(wr_ptr);
  assign rd_ptr_gray = binary_to_gray(rd_ptr);

endmodule

rtl/fifo/fifo_tb.sv
// rtl/fifo/fifo_tb.sv - UPDATED
`timescale 1ns / 1ps

module fifo_tb;

  reg         clk;
  reg  [31:0] data_in;  // Changed from din to data_in
  wire [31:0] data_out;  // Changed from dout to data_out
  reg  [31:0] rdata;
  wire        empty;  // Now it's wire, not reg
  reg         rd_en;
  reg         wr_en;
  wire        full;
  reg         rst_n;  // Changed from rstn to rst_n
  reg         stop;

  // Instantiation with CORRECT names
  sync_fifo #(
      .DATA_WIDTH(32),
      .FIFO_DEPTH(16)
  ) u_sync_fifo (
      .rst_n   (rst_n),     // rst_n
      .wr_en   (wr_en),
      .rd_en   (rd_en),
      .clk     (clk),
      .data_in (data_in),   // data_in
      .data_out(data_out),  // data_out
      .empty   (empty),
      .full    (full)
  );

  // Clock generation: 50 MHz (20ns period)
  always #10 clk = ~clk;

  // Dump waveform
  initial begin
    $dumpfile("fifo.vcd");
    $dumpvars(0, fifo_tb);
  end

  initial begin
    clk = 0;
    rst_n = 0;
    wr_en = 0;
    rd_en = 0;
    stop = 0;
    data_in = 0;

    #50 rst_n = 1;
    $display("[%0t] Reset released", $time);
  end

  // Write process
  initial begin
    @(posedge rst_n);
    @(posedge clk);

    for (int i = 0; i < 20; i = i + 1) begin

      // Wait until there is space in fifo
      while (full) begin
        @(posedge clk);
        $display("[%0t] FIFO is full, waiting...", $time);
      end

      // Drive new values into FIFO
      wr_en   = $urandom_range(0, 1);  // Random write enable
      data_in = $urandom;  // Random data
      $display("[%0t] Write[%0d]: wr_en=%0d data_in=0x%08h", $time, i, wr_en, data_in);

      @(posedge clk);
      wr_en = 0;  // Disable write after one cycle
    end

    stop = 1;
    $display("[%0t] Write process finished", $time);
  end

  // Read process
  initial begin
    @(posedge rst_n);
    @(posedge clk);

    while (!stop) begin
      // Wait until there is data in fifo
      while (empty) begin
        rd_en = 0;
        $display("[%0t] FIFO is empty, waiting...", $time);
        @(posedge clk);
      end

      // Sample new values from FIFO
      rd_en = $urandom_range(0, 1);  // Random read enable
      @(posedge clk);
      rdata = data_out;
      $display("[%0t] Read: rd_en=%0d data_out=0x%08h", $time, rd_en, rdata);
      rd_en = 0;
    end

    #500;
    $display("[%0t] Simulation finished", $time);
    $finish;
  end

  // Timeout
  initial begin
    #10000;
    $display("[%0t] Timeout - simulation too long", $time);
    $finish;
  end

endmodule

rtl/fifo/fifo.vcd
$date
	Wed Jan 21 18:59:35 2026
$end
$version
	Icarus Verilog
$end
$timescale
	1ps
$end
$scope module fifo_tb $end
$var wire 1 ! full $end
$var wire 1 " empty $end
$var wire 32 # data_out [31:0] $end
$var reg 1 $ clk $end
$var reg 32 % data_in [31:0] $end
$var reg 1 & rd_en $end
$var reg 32 ' rdata [31:0] $end
$var reg 1 ( rst_n $end
$var reg 1 ) stop $end
$var reg 1 * wr_en $end
$scope module u_sync_fifo $end
$var wire 1 $ clk $end
$var wire 32 + data_in [31:0] $end
$var wire 32 , data_out [31:0] $end
$var wire 1 ! full $end
$var wire 1 & rd_en $end
$var wire 1 ( rst_n $end
$var wire 1 * wr_en $end
$var wire 5 - wr_ptr_gray [4:0] $end
$var wire 5 . rd_ptr_gray [4:0] $end
$var wire 1 " empty $end
$var parameter 32 / ADDR_WIDTH $end
$var parameter 32 0 DATA_WIDTH $end
$var parameter 32 1 FIFO_DEPTH $end
$var reg 5 2 rd_ptr [4:0] $end
$var reg 5 3 wr_ptr [4:0] $end
$scope function binary_to_gray $end
$var reg 5 4 bin [4:0] $end
$upscope $end
$upscope $end
$scope begin $ivl_for_loop0 $end
$var integer 32 5 i [31:0] $end
$upscope $end
$upscope $end
$enddefinitions $end
$comment Show the parameter values. $end
$dumpall
b10000 1
b100000 0
b100 /
$end
#0
$dumpvars
b0 5
b0 4
b0 3
b0 2
b0 .
b0 -
bx ,
b0 +
0*
0)
0(
bx '
0&
b0 %
0$
bx #
1"
0!
$end
#10000
1$
#20000
0$
#30000
1$
#40000
0$
#50000
1$
1(
#60000
0$
#70000
b1 -
b1 4
0"
b1 3
b1000000100010010101111010000001 #
b1000000100010010101111010000001 ,
b1000000100010010101111010000001 %
b1000000100010010101111010000001 +
1*
1$
#80000
0$
#90000
bx #
bx ,
b1 .
1"
b1 2
1&
b110001111100000101011001100011 %
b110001111100000101011001100011 +
b1 5
0*
1$
#100000
0$
#110000
b11 -
b10 4
0"
b10 3
b110010110000101000010001100101 #
b110010110000101000010001100101 ,
b110010110000101000010001100101 %
b110010110000101000010001100101 +
1*
b10 5
0&
1$
#120000
0$
#130000
bx #
bx ,
b11 .
1"
b10 2
1&
b10000000111100111110001100000001 %
b10000000111100111110001100000001 +
b11 5
0*
1$
#140000
0$
#150000
b10 -
b11 4
0"
b11 3
b10011110100011011100110100111101 #
b10011110100011011100110100111101 ,
b10011110100011011100110100111101 %
b10011110100011011100110100111101 +
1*
b100 5
0&
1$
#160000
0$
#170000
b11000110001011011111011110001100 #
b11000110001011011111011110001100 ,
b10 .
b110 -
b11 4
b11 2
b100 3
1&
b11000110001011011111011110001100 %
b11000110001011011111011110001100 +
b101 5
1*
1$
#180000
0$
#190000
b1010101000100111101001010101010 %
b1010101000100111101001010101010 +
b110 5
0*
0&
b11000110001011011111011110001100 '
1$
#200000
0$
#210000
b111 -
b101 4
b101 3
b111011110100100111001001110111 %
b111011110100100111001001110111 +
1*
b111 5
1$
#220000
0$
#230000
b101 -
b111011110100100111001001110111 #
b111011110100100111001001110111 ,
b110 .
b110 4
b110 3
b100 2
b1100111011101101001011011001110 %
b1100111011101101001011011001110 +
b1000 5
1*
1&
1$
#240000
0$
#250000
b1100111011101101001011011001110 #
b1100111011101101001011011001110 ,
b111 .
b101 4
b101 2
1&
b111011110100100111001001110111 '
b1100010110010100100111011000101 %
b1100010110010100100111011000101 +
b1001 5
0*
1$
#260000
0$
#270000
b110010101001110010011001100101 %
b110010101001110010011001100101 +
b1010 5
0&
b1100111011101101001011011001110 '
1$
#280000
0$
#290000
b10000101011100111000011100001010 %
b10000101011100111000011100001010 +
b1011 5
1$
#300000
0$
#310000
b100 -
b1001110110011001100110010011101 #
b1001110110011001100110010011101 ,
b101 .
b111 4
b111 3
0"
b110 2
b1001110110011001100110010011101 %
b1001110110011001100110010011101 +
1*
b1100 5
1&
1$
#320000
0$
#330000
0&
b1001110110011001100110010011101 '
b1001100000111011100000010011 %
b1001100000111011100000010011 +
b1101 5
0*
1$
#340000
0$
#350000
b1100 -
b1000 4
b1000 3
b1101010101001100010101011010101 %
b1101010101001100010101011010101 +
1*
b1110 5
1$
#360000
0$
#370000
b1101010101001100010101011010101 #
b1101010101001100010101011010101 ,
b100 .
b111 4
b111 2
1&
b1010111010101100011111010101110 %
b1010111010101100011111010101110 +
b1111 5
0*
1$
#380000
0$
#390000
b1101 -
b1001 4
b1001 3
b10000101000010010110010100001010 %
b10000101000010010110010100001010 +
1*
b10000 5
0&
b1101010101001100010101011010101 '
1$
#400000
0$
#410000
b10000101000010010110010100001010 #
b10000101000010010110010100001010 ,
b1100 .
b1000 4
b1000 2
1&
b11110001100010100110000111100 %
b11110001100010100110000111100 +
b10001 5
0*
1$
#420000
0$
#430000
b1111 -
b1101100010010110011010011011000 #
b1101100010010110011010011011000 ,
b1101 .
b1010 4
b1010 3
0"
b1001 2
b1101100010010110011010011011000 %
b1101100010010110011010011011000 +
1*
b10010 5
1&
b10000101000010010110010100001010 '
1$
#440000
0$
#450000
b1000100100010100001001010001001 #
b1000100100010100001001010001001 ,
b1111 .
b1110 -
b1010 4
b1010 2
b1011 3
1&
b1101100010010110011010011011000 '
b1000100100010100001001010001001 %
b1000100100010100001001010001001 +
b10011 5
1*
1$
#460000
0$
#470000
bx #
bx ,
b1110 .
b1011 4
1"
b1011 2
1)
b10100 5
0*
1&
b1000100100010100001001010001001 '
1$
#480000
0$
#490000
0&
bx '
1$
