rtl/fifo/sync_fifo.sv
module sync_fifo #(
    parameter int DEPTH  = 8,
    parameter int DWIDTH = 16
) (
    input  logic              rstn,   // Active low reset
    input  logic              clk,    // Clock
    input  logic              wr_en,  // Write enable
    input  logic              rd_en,  // Read enable
    input  logic [DWIDTH-1:0] din,    // Data written into FIFO
    output logic [DWIDTH-1:0] dout,   // Data read from FIFO
    output logic              empty,  // FIFO is empty when high
    output logic              full    // FIFO is full when high
);

  //write side
  logic [$clog2(DEPTH)-1:0] wptr, rptr;
  logic [DWIDTH-1:0] fifo[DEPTH];  // width x depth = mem size

  always_ff @(posedge clk or negedge rstn) begin
    if (!rstn) begin
      wptr <= '0;
    end else begin
      if (wr_en & !full) begin
        fifo[wptr] <= din;
        wptr <= wptr + 1;
      end
    end
  end

  initial begin
    $monitor("[%0t] [FIFO] wr_en=%0b din=0x%0h rd_en=%0b dout=0x%0h empty=%0b full=%0b", $time,
             wr_en, din, rd_en, dout, empty, full);
  end

  //read side
  always_ff @(posedge clk or negedge rstn) begin
    if (!rstn) begin
      rptr <= '0;
    end else begin
      if (rd_en & !empty) begin
        dout <= fifo[rptr];
        rptr <= rptr + 1;
      end
    end
  end

  always_comb begin
    full  = (wptr + 1) == rptr;
    empty = wptr == rptr;
  end

endmodule

rtl/fifo/fifo_tb.sv
module fifo_tb;

  reg         clk;
  reg  [15:0] din;
  wire [15:0] dout;
  reg  [15:0] rdata;
  reg         empty;
  reg         rd_en;
  reg         wr_en;
  wire        full;
  reg         rstn;
  reg         stop;

  sync_fifo u_sync_fifo (
      .rstn (rstn),
      .wr_en(wr_en),
      .rd_en(rd_en),
      .clk  (clk),
      .din  (din),
      .dout (dout),
      .empty(empty),
      .full (full)
  );

  always #10 clk <= ~clk;

  initial begin
    clk   <= 0;
    rstn  <= 0;
    wr_en <= 0;
    rd_en <= 0;
    stop  <= 0;

    #50 rstn <= 1;
  end

  initial begin
    @(posedge clk);

    for (int i = 0; i < 20; i = i + 1) begin

      // Wait until there is space in fifo
      while (full) begin
        @(posedge clk);
        $display("[%0t] FIFO is full, wait for reads to happen", $time);
      end
      ;

      // Drive new values into FIFO
      wr_en <= $random;
      din   <= $random;
      $display("[%0t] clk i=%0d wr_en=%0d din=0x%0h ", $time, i, wr_en, din);

      // Wait for next clock edge
      @(posedge clk);
    end

    stop = 1;
  end

  initial begin
    @(posedge clk);

    while (!stop) begin
      // Wait until there is data in fifo
      while (empty) begin
        rd_en <= 0;

        $display("[%0t] FIFO is empty, wait for writes to happen", $time);
        @(posedge clk);
      end
      ;

      // Sample new values from FIFO at random pace
      rd_en <= $random;
      @(posedge clk);
      rdata <= dout;
      $display("[%0t] clk rd_en=%0d rdata=0x%0h ", $time, rd_en, rdata);
    end

    #500 $finish;
  end

endmodule

results/plots/fifo.vcd
$date
	Sat Jan 10 00:21:22 2026
$end
$version
	Icarus Verilog
$end
$timescale
	1s
$end
$scope module fifo_tb $end
$var wire 1 ! full $end
$var wire 1 " empty $end
$var wire 16 # dout [15:0] $end
$var reg 1 $ clk $end
$var reg 16 % din [15:0] $end
$var reg 1 & rd_en $end
$var reg 16 ' rdata [15:0] $end
$var reg 1 ( rstn $end
$var reg 1 ) stop $end
$var reg 1 * wr_en $end
$scope module u_sync_fifo $end
$var wire 1 $ clk $end
$var wire 16 + din [15:0] $end
$var wire 1 & rd_en $end
$var wire 1 ( rstn $end
$var wire 1 * wr_en $end
$var parameter 32 , DEPTH $end
$var parameter 32 - DWIDTH $end
$var reg 16 . dout [15:0] $end
$var reg 1 " empty $end
$var reg 1 ! full $end
$var reg 3 / rptr [2:0] $end
$var reg 3 0 wptr [2:0] $end
$upscope $end
$scope begin $ivl_for_loop0 $end
$var integer 32 1 i [31:0] $end
$upscope $end
$upscope $end
$enddefinitions $end
$comment Show the parameter values. $end
$dumpall
b10000 -
b1000 ,
$end
#0
$dumpvars
b0 1
b0 0
b0 /
bx .
bx +
0*
0)
0(
bx '
0&
bx %
0$
bx #
1"
0!
$end
#10
b101111010000001 %
b101111010000001 +
1$
#20
0$
#30
b101011001100011 %
b101011001100011 +
1*
b1 1
1$
#40
0$
#50
0"
b1 0
b1001100110001101 %
b1001100110001101 +
b10 1
1$
1(
#60
0$
#70
b10 0
1&
b101001000010010 %
b101001000010010 +
b11 1
1$
#80
0$
#90
b1 /
b101011001100011 #
b101011001100011 .
b11 0
b1100110100111101 %
b1100110100111101 +
0*
b100 1
1$
#100
0$
#110
b10 /
b1001100110001101 #
b1001100110001101 .
b101011001100011 '
b1111011110001100 %
b1111011110001100 +
1*
b101 1
1$
#120
0$
#130
b11 /
b101001000010010 #
b101001000010010 .
b100 0
b1101001010101010 %
b1101001010101010 +
0&
b1001100110001101 '
b110 1
1$
#140
0$
#150
b101 0
b101001000010010 '
b111001001110111 %
b111001001110111 +
b111 1
1$
#160
0$
#170
b110 0
b1001011011001110 %
b1001011011001110 +
0*
1&
b1000 1
1$
#180
0$
#190
b100 /
b1111011110001100 #
b1111011110001100 .
0&
b100111011000101 %
b100111011000101 +
b1001 1
1$
#200
0$
#210
b10011001100101 %
b10011001100101 +
1*
1&
b1111011110001100 '
b1010 1
1$
#220
0$
#230
b111 0
b101 /
b1101001010101010 #
b1101001010101010 .
0&
b1000011100001010 %
b1000011100001010 +
b1011 1
1$
#240
0$
#250
b0 0
b1100110010011101 %
b1100110010011101 +
0*
b1101001010101010 '
b1100 1
1$
#260
0$
#270
1&
b1011100000010011 %
b1011100000010011 +
b1101 1
1$
#280
0$
#290
b110 /
b111001001110111 #
b111001001110111 .
b10101011010101 %
b10101011010101 +
1*
b1110 1
1$
#300
0$
#310
b1 0
b111 /
b10011001100101 #
b10011001100101 .
b111001001110111 '
b11111010101110 %
b11111010101110 +
0*
b1111 1
1$
#320
0$
#330
b0 /
b1000011100001010 #
b1000011100001010 .
b110010100001010 %
b110010100001010 +
1*
b10011001100101 '
b10000 1
1$
#340
0$
#350
b10 0
b1 /
b10101011010101 #
b10101011010101 .
0&
b1000011100001010 '
b100110000111100 %
b100110000111100 +
0*
b10001 1
1$
#360
0$
#370
b11010011011000 %
b11010011011000 +
1*
b10101011010101 '
b10010 1
1$
#380
0$
#390
b11 0
1&
b1001010001001 %
b1001010001001 +
0*
b10011 1
1$
#400
0$
#410
b10 /
b110010100001010 #
b110010100001010 .
0&
1)
b10100 1
1$
#420
0$
#430
b110010100001010 '
1$
